trmnl_colors/__init__.py
trmnl_colors/constants.py
trmnl_colors/functions.py
trmnl_colors/test.py
trmnl_colors-4.0.9.dist-info/LICENSE
trmnl_colors-4.0.9.dist-info/METADATA
trmnl_colors-4.0.9.dist-info/WHEEL
trmnl_colors-4.0.9.dist-info/top_level.txt
trmnl_colors-4.0.9.dist-info/RECORD
