Metadata-Version: 2.1
Name: trmnl-colors
Version: 4.0.9
Summary: Colors, text formats, decorations and much more for TERMINAL
Home-page: https://github.com/Idrisvohra9/colors
Author: Idris-Vohra
Author-email: idrishaider987@gmail.com
License: MIT
Requires-Python: >=3.8
License-File: LICENSE
